pyemon/__init__.py
pyemon/cli.py
pyemon/command.py
pyemon/directory.py
pyemon/list.py
pyemon/option.py
pyemon/path.py
pyemon/status.py
pyemon/string.py
pyemon/task.py
pyemon/time.py
pyemon/scripts/.gitignore
pyemon/scripts/MANIFEST.in
pyemon/scripts/README.md
pyemon/scripts/pyproject.toml
pyemon/scripts/setup.py
pyemon/scripts/tests/test.py
pyemon/tasks/package/build.py
pyemon/tasks/package/init.py
pyemon/tasks/package/install.py
pyemon/tasks/package/test.py
pyemon/tasks/package/upload.py
pyemon/tasks/task/run.py
pyemon-0.2.2.dist-info/LICENSE
pyemon-0.2.2.dist-info/METADATA
pyemon-0.2.2.dist-info/WHEEL
pyemon-0.2.2.dist-info/entry_points.txt
pyemon-0.2.2.dist-info/top_level.txt
pyemon-0.2.2.dist-info/RECORD
